sensirion_i2c_sf06_lf/__init__.py
sensirion_i2c_sf06_lf/commands.py
sensirion_i2c_sf06_lf/device.py
sensirion_i2c_sf06_lf/result_types.py
sensirion_i2c_sf06_lf/version.py
sensirion_i2c_sf06_lf-0.1.0.dist-info/LICENSE
sensirion_i2c_sf06_lf-0.1.0.dist-info/METADATA
sensirion_i2c_sf06_lf-0.1.0.dist-info/WHEEL
sensirion_i2c_sf06_lf-0.1.0.dist-info/top_level.txt
sensirion_i2c_sf06_lf-0.1.0.dist-info/RECORD
